{
  "_class": "sharedStyle",
  "do_objectID": "CCC94B66-FA76-4ED9-A202-C5B0EFEF3D1A",
  "name": "Body/Bold/Black/Center",
  "value": {
    "_class": "style",
    "endMarkerType": 0,
    "miterLimit": 10,
    "startMarkerType": 0,
    "textStyle": {
      "_class": "textStyle",
      "encodedAttributes": {
        "MSAttributedStringColorAttribute": {
          "_class": "color",
          "alpha": 1,
          "blue": 0.2784313725490196,
          "green": 0.06274509803921569,
          "red": 0.05098039215686274
        },
        "MSAttributedStringFontAttribute": {
          "_class": "fontDescriptor",
          "attributes": {
            "name": "IBMPlexSans-Medium",
            "size": 16
          }
        },
        "kerning": 0,
        "paragraphStyle": {
          "_class": "paragraphStyle",
          "alignment": 2,
          "allowsDefaultTighteningForTruncation": 0,
          "maximumLineHeight": 24,
          "minimumLineHeight": 24,
          "paragraphSpacing": 8
        }
      },
      "verticalAlignment": 0
    },
    "windingRule": 1
  }
}