{
  "_class": "symbolInstance",
  "booleanOperation": -1,
  "clippingMaskMode": 0,
  "do_objectID": "5E68B4D1-F281-434E-8381-AAB4FE6602A6",
  "exportOptions": {
    "_class": "exportOptions",
    "do_objectID": "73D3F7A1-EE07-47D6-87EC-0E5377DD1C30",
    "exportFormats": [
    ],
    "includedLayerIds": [
    ],
    "layerOptions": 0,
    "shouldTrim": false
  },
  "frame": {
    "_class": "rect",
    "constrainProportions": false,
    "do_objectID": "C047C316-D8A8-4B8D-87B1-0F90D350E595",
    "height": 24,
    "width": 24,
    "x": 301,
    "y": 1
  },
  "hasClippingMask": false,
  "horizontalSpacing": 0,
  "isFixedToViewport": false,
  "isFlippedHorizontal": false,
  "isFlippedVertical": false,
  "isLocked": false,
  "isVisible": true,
  "layerListExpandedType": 0,
  "name": "icons/chevron-down/grey",
  "nameIsFixed": false,
  "overrideValues": [
  ],
  "resizingConstraint": 63,
  "resizingType": 0,
  "rotation": 0,
  "scale": 1,
  "shouldBreakMaskChain": false,
  "style": {
    "_class": "style",
    "do_objectID": "3FB1F65B-A05E-4838-A273-51613AE63B10",
    "endMarkerType": 0,
    "miterLimit": 10,
    "startMarkerType": 0,
    "windingRule": 1
  },
  "symbolID": "DE9E5F4E-B929-46D9-9D56-90BD68B1E54B",
  "verticalSpacing": 0
}