{
  "_class": "text",
  "attributedString": {
    "_class": "attributedString",
    "attributes": [
      {
        "_class": "stringAttribute",
        "attributes": {
          "MSAttributedStringColorAttribute": {
            "_class": "color",
            "alpha": 1,
            "blue": 0.2784313725490196,
            "green": 0.06274509803921569,
            "red": 0.05098039215686274
          },
          "MSAttributedStringFontAttribute": {
            "_class": "fontDescriptor",
            "attributes": {
              "name": "IBMPlexSans-Light",
              "size": 14.4
            }
          },
          "kerning": 0,
          "paragraphStyle": {
            "_class": "paragraphStyle",
            "alignment": 2,
            "allowsDefaultTighteningForTruncation": 0,
            "maximumLineHeight": 21.6,
            "minimumLineHeight": 21.6,
            "paragraphSpacing": 7.2
          }
        },
        "length": 103,
        "location": 0
      }
    ],
    "string": "“VodafoneZiggo Netherlands saved two hours per day updating CRM data with Olbico Master Data Platform.”"
  },
  "automaticallyDrawOnUnderlyingPath": false,
  "booleanOperation": -1,
  "clippingMaskMode": 0,
  "do_objectID": "A01F812A-3B00-496E-83B2-FD7158843C74",
  "dontSynchroniseWithSymbol": false,
  "exportOptions": {
    "_class": "exportOptions",
    "do_objectID": "7C0D825E-65F2-4884-802F-C932633C65F3",
    "exportFormats": [
    ],
    "includedLayerIds": [
    ],
    "layerOptions": 0,
    "shouldTrim": false
  },
  "frame": {
    "_class": "rect",
    "constrainProportions": false,
    "do_objectID": "006F37E1-62B0-4ADA-B085-0A39345A4958",
    "height": 86.4,
    "width": 202.5,
    "x": 13.5,
    "y": 99
  },
  "glyphBounds": "{{4, 5}, {195, 77}}",
  "hasClippingMask": false,
  "isFixedToViewport": false,
  "isFlippedHorizontal": false,
  "isFlippedVertical": false,
  "isLocked": false,
  "isVisible": true,
  "layerListExpandedType": 0,
  "lineSpacingBehaviour": 2,
  "name": "“VodafoneZiggo Nethe",
  "nameIsFixed": false,
  "resizingConstraint": 51,
  "resizingType": 0,
  "rotation": 0,
  "sharedStyleID": "28BB6559-59FC-4D0D-AD03-B79D9C9D807C",
  "shouldBreakMaskChain": false,
  "style": {
    "_class": "style",
    "blur": {
      "_class": "blur",
      "center": "{0.5, 0.5}",
      "do_objectID": "150DB2F9-3C5B-44B6-A33A-71A1E4A45234",
      "isEnabled": false,
      "motionAngle": 0,
      "radius": 9,
      "saturation": 1,
      "type": 0
    },
    "do_objectID": "A4D8FF17-C933-41A3-9FDA-442746BE9FA9",
    "endMarkerType": 0,
    "miterLimit": 10,
    "startMarkerType": 0,
    "textStyle": {
      "_class": "textStyle",
      "do_objectID": "836DC58F-B8AF-4E98-A856-3D85C1FC9B93",
      "encodedAttributes": {
        "MSAttributedStringColorAttribute": {
          "_class": "color",
          "alpha": 1,
          "blue": 0.2784313725490196,
          "green": 0.06274509803921569,
          "red": 0.05098039215686274
        },
        "MSAttributedStringFontAttribute": {
          "_class": "fontDescriptor",
          "attributes": {
            "name": "IBMPlexSans-Light",
            "size": 14.4
          }
        },
        "kerning": 0,
        "paragraphStyle": {
          "_class": "paragraphStyle",
          "alignment": 2,
          "allowsDefaultTighteningForTruncation": 0,
          "maximumLineHeight": 21.6,
          "minimumLineHeight": 21.6,
          "paragraphSpacing": 7.2
        }
      },
      "verticalAlignment": 0
    },
    "windingRule": 1
  },
  "textBehaviour": 2
}