{
  "_class": "text",
  "attributedString": {
    "_class": "attributedString",
    "attributes": [
      {
        "_class": "stringAttribute",
        "attributes": {
          "MSAttributedStringColorAttribute": {
            "_class": "color",
            "alpha": 1,
            "blue": 0.2784313725490196,
            "green": 0.06274509803921569,
            "red": 0.05098039215686274
          },
          "MSAttributedStringFontAttribute": {
            "_class": "fontDescriptor",
            "attributes": {
              "name": "IBMPlexSans-Light",
              "size": 27
            }
          },
          "kerning": 0,
          "paragraphStyle": {
            "_class": "paragraphStyle",
            "alignment": 0,
            "allowsDefaultTighteningForTruncation": 0,
            "maximumLineHeight": 32.4,
            "minimumLineHeight": 32.4
          }
        },
        "length": 103,
        "location": 0
      }
    ],
    "string": "“VodafoneZiggo Netherlands saved two hours per day updating CRM data with Olbico Master Data Platform.”"
  },
  "automaticallyDrawOnUnderlyingPath": false,
  "booleanOperation": -1,
  "clippingMaskMode": 0,
  "do_objectID": "A408FAC0-D6C9-4A6F-A6D8-F2A6976AF373",
  "dontSynchroniseWithSymbol": false,
  "exportOptions": {
    "_class": "exportOptions",
    "do_objectID": "10D4953C-DF65-41F2-93D4-C36898309B68",
    "exportFormats": [
    ],
    "includedLayerIds": [
    ],
    "layerOptions": 0,
    "shouldTrim": false
  },
  "frame": {
    "_class": "rect",
    "constrainProportions": false,
    "do_objectID": "CE6A263F-2742-4251-9FFF-D213410BE6EC",
    "height": 128.7,
    "width": 360,
    "x": 36,
    "y": 36
  },
  "glyphBounds": "{{1, 6}, {353, 118}}",
  "hasClippingMask": false,
  "isFixedToViewport": false,
  "isFlippedHorizontal": false,
  "isFlippedVertical": false,
  "isLocked": false,
  "isVisible": true,
  "layerListExpandedType": 0,
  "lineSpacingBehaviour": 2,
  "name": "“VodafoneZiggo Nethe",
  "nameIsFixed": false,
  "resizingConstraint": 51,
  "resizingType": 0,
  "rotation": 0,
  "sharedStyleID": "99E7583B-5BC5-4C04-9E8D-85D23CE58517",
  "shouldBreakMaskChain": false,
  "style": {
    "_class": "style",
    "blur": {
      "_class": "blur",
      "center": "{0.5, 0.5}",
      "do_objectID": "1938F4E5-E746-44BD-BE63-5CF23864765B",
      "isEnabled": false,
      "motionAngle": 0,
      "radius": 9,
      "saturation": 1,
      "type": 0
    },
    "do_objectID": "5AE749FF-C740-42D7-9062-D83BC0B58D93",
    "endMarkerType": 0,
    "miterLimit": 10,
    "startMarkerType": 0,
    "textStyle": {
      "_class": "textStyle",
      "do_objectID": "6B9A201B-3243-47F7-B4DF-562D15B0B5DF",
      "encodedAttributes": {
        "MSAttributedStringColorAttribute": {
          "_class": "color",
          "alpha": 1,
          "blue": 0.2784313725490196,
          "green": 0.06274509803921569,
          "red": 0.05098039215686274
        },
        "MSAttributedStringFontAttribute": {
          "_class": "fontDescriptor",
          "attributes": {
            "name": "IBMPlexSans-Light",
            "size": 27
          }
        },
        "kerning": 0,
        "paragraphStyle": {
          "_class": "paragraphStyle",
          "alignment": 0,
          "allowsDefaultTighteningForTruncation": 0,
          "maximumLineHeight": 32.4,
          "minimumLineHeight": 32.4
        }
      },
      "verticalAlignment": 0
    },
    "windingRule": 1
  },
  "textBehaviour": 2
}