{
  "_class": "shapePath",
  "booleanOperation": -1,
  "clippingMaskMode": 0,
  "do_objectID": "3F192286-4989-450A-B778-F001981E858C",
  "edited": true,
  "exportOptions": {
    "_class": "exportOptions",
    "exportFormats": [
    ],
    "includedLayerIds": [
    ],
    "layerOptions": 0,
    "shouldTrim": false
  },
  "frame": {
    "_class": "rect",
    "constrainProportions": false,
    "do_objectID": "79E48260-536B-4685-B447-9F3A57ACC3E5",
    "height": 97,
    "width": 2,
    "x": 47.79399993392508,
    "y": 1.5
  },
  "hasClippingMask": false,
  "isClosed": false,
  "isFixedToViewport": false,
  "isFlippedHorizontal": false,
  "isFlippedVertical": false,
  "isLocked": false,
  "isVisible": true,
  "layerListExpandedType": 0,
  "name": "Path",
  "nameIsFixed": false,
  "pointRadiusBehaviour": 1,
  "points": [
    {
      "_class": "curvePoint",
      "cornerRadius": 0,
      "curveFrom": "{0.69914813369748918, -0.30927835051545455}",
      "curveMode": 1,
      "curveTo": "{0.69914813369748918, -0.30927835051545455}",
      "hasCurveFrom": false,
      "hasCurveTo": false,
      "point": "{0.69914813369769035, 0.0038363395250055315}"
    },
    {
      "_class": "curvePoint",
      "cornerRadius": 0,
      "curveFrom": "{0.69914813369748918, 1.0030309271538771}",
      "curveMode": 1,
      "curveTo": "{0.69914813369748918, 1.0030309271538771}",
      "hasCurveFrom": false,
      "hasCurveTo": false,
      "point": "{0.69914813369769035, 0.99570167457654657}"
    }
  ],
  "resizingConstraint": 63,
  "resizingType": 0,
  "rotation": -90,
  "shouldBreakMaskChain": false,
  "style": {
    "_class": "style",
    "borders": [
      {
        "_class": "border",
        "color": {
          "_class": "color",
          "alpha": 1,
          "blue": 0.5725490196078431,
          "green": 0.615686274509804,
          "red": 0.996078431372549
        },
        "fillType": 0,
        "isEnabled": true,
        "position": 0,
        "thickness": 1
      }
    ],
    "do_objectID": "B05A2A43-1F04-4FDF-9B6A-16A755A71A91",
    "endMarkerType": 0,
    "miterLimit": 10,
    "startMarkerType": 0,
    "windingRule": 1
  }
}