{
  "_class": "symbolMaster",
  "allowsOverrides": true,
  "backgroundColor": {
    "_class": "color",
    "alpha": 1,
    "blue": 1,
    "do_objectID": "651BC6F9-587C-4702-A01E-648E0BEFC735",
    "green": 1,
    "red": 1
  },
  "booleanOperation": 0,
  "changeIdentifier": 1134,
  "clippingMaskMode": 0,
  "do_objectID": "12515065-DC4A-4D21-9C32-975159F9B724",
  "exportOptions": {
    "_class": "exportOptions",
    "exportFormats": [
    ],
    "includedLayerIds": [
    ],
    "layerOptions": 0,
    "shouldTrim": false
  },
  "frame": {
    "_class": "rect",
    "constrainProportions": false,
    "do_objectID": "AEF24D99-4D4F-4112-988F-B4DD4EBACA21",
    "height": 60,
    "width": 112,
    "x": 1956,
    "y": 151
  },
  "groupLayout": {
    "_class": "MSImmutableFreeformGroupLayout"
  },
  "hasBackgroundColor": false,
  "hasClickThrough": true,
  "hasClippingMask": false,
  "horizontalRulerData": {
    "_class": "rulerData",
    "base": 0,
    "do_objectID": "3372991D-5504-4F21-82B2-C4C881640724",
    "guides": [
    ]
  },
  "includeBackgroundColorInExport": true,
  "includeBackgroundColorInInstance": false,
  "includeInCloudUpload": true,
  "isFixedToViewport": false,
  "isFlippedHorizontal": false,
  "isFlippedVertical": false,
  "isFlowHome": false,
  "isLocked": false,
  "isVisible": true,
  "layerListExpandedType": 0,
  "layers": [
    {
      "class": "symbolInstance",
      "id": "9F5E2402-E186-4128-9BB4-E893ABD51FB3"
    }
  ],
  "name": "button/large",
  "nameIsFixed": true,
  "overrideProperties": [
    {
      "_class": "MSImmutableOverrideProperty",
      "canOverride": true,
      "overrideName": "9F5E2402-E186-4128-9BB4-E893ABD51FB3_symbolID"
    }
  ],
  "resizesContent": false,
  "resizingConstraint": 63,
  "resizingType": 0,
  "rotation": 0,
  "shouldBreakMaskChain": true,
  "style": {
    "_class": "style",
    "do_objectID": "4D11A428-651E-4DBE-849A-298FD71DF495",
    "endMarkerType": 0,
    "miterLimit": 10,
    "startMarkerType": 0,
    "windingRule": 1
  },
  "symbolID": "668A852D-1780-4FA4-8F02-491AF9F96D08",
  "userInfo": {
    "io.magicsketch.mirror": {
      "highestQuality": 1
    }
  },
  "verticalRulerData": {
    "_class": "rulerData",
    "base": 0,
    "do_objectID": "1C2D1769-916B-4DFB-9FB4-930FC2F5F951",
    "guides": [
    ]
  }
}