{
  "_class": "group",
  "booleanOperation": -1,
  "clippingMaskMode": 0,
  "do_objectID": "C072DCD8-61CB-47D6-BB45-7853525CD30E",
  "exportOptions": {
    "_class": "exportOptions",
    "do_objectID": "58AF1879-3324-4BCA-BE15-E53592FD5CD0",
    "exportFormats": [
    ],
    "includedLayerIds": [
    ],
    "layerOptions": 0,
    "shouldTrim": false
  },
  "frame": {
    "_class": "rect",
    "constrainProportions": false,
    "do_objectID": "7DE4FAA4-0189-4451-854A-CFA477C1F71D",
    "height": 369,
    "width": 440.0000000000003,
    "x": 739.9999999999999,
    "y": 141
  },
  "groupLayout": {
    "_class": "MSImmutableFreeformGroupLayout",
    "do_objectID": "2FD7C2BE-8239-4E71-B392-4E9F6DCC27C8"
  },
  "hasClickThrough": false,
  "hasClippingMask": false,
  "isFixedToViewport": false,
  "isFlippedHorizontal": false,
  "isFlippedVertical": false,
  "isLocked": false,
  "isVisible": true,
  "layerListExpandedType": 0,
  "layers": [
    {
      "class": "text",
      "id": "9BE3C1F1-5D8C-4E21-9659-0B36F97FC523"
    },
    {
      "class": "text",
      "id": "D217A377-B9C3-479D-80CF-9F85FC3BF13F"
    },
    {
      "class": "text",
      "id": "9CB2B671-8CE8-4721-8989-268FCA296530"
    },
    {
      "class": "symbolInstance",
      "id": "589A347C-1E9D-44B0-BE29-1597213483E3"
    }
  ],
  "name": "Group",
  "nameIsFixed": false,
  "resizingConstraint": 63,
  "resizingType": 0,
  "rotation": 0,
  "shouldBreakMaskChain": false,
  "style": {
    "_class": "style",
    "do_objectID": "004ADCD0-B653-4575-A164-C0B038F2909C",
    "endMarkerType": 0,
    "miterLimit": 10,
    "startMarkerType": 0,
    "windingRule": 1
  }
}