{
  "_class": "symbolInstance",
  "booleanOperation": -1,
  "clippingMaskMode": 0,
  "do_objectID": "AD975627-6D4A-4B70-85FE-DFBF0041CD20",
  "exportOptions": {
    "_class": "exportOptions",
    "do_objectID": "70B19DCB-9B7D-466B-979F-BBDB07A3DDB5",
    "exportFormats": [
    ],
    "includedLayerIds": [
    ],
    "layerOptions": 0,
    "shouldTrim": false
  },
  "frame": {
    "_class": "rect",
    "constrainProportions": true,
    "do_objectID": "F2FBFF86-D82C-44FE-B5A7-805475E4EF99",
    "height": 15,
    "width": 15,
    "x": 22,
    "y": 6
  },
  "hasClippingMask": false,
  "horizontalSpacing": 0,
  "isFixedToViewport": false,
  "isFlippedHorizontal": false,
  "isFlippedVertical": false,
  "isLocked": false,
  "isVisible": true,
  "layerListExpandedType": 0,
  "name": "icons/chevron-down/grey",
  "nameIsFixed": false,
  "overrideValues": [
  ],
  "resizingConstraint": 63,
  "resizingType": 0,
  "rotation": 0,
  "scale": 1,
  "shouldBreakMaskChain": false,
  "style": {
    "_class": "style",
    "do_objectID": "AEB706F6-552D-4C28-90BD-128851746B38",
    "endMarkerType": 0,
    "miterLimit": 10,
    "startMarkerType": 0,
    "windingRule": 1
  },
  "symbolID": "7EBB9392-5518-44F0-A27C-EE97F24C1F9B",
  "verticalSpacing": 0
}