{
  "_class": "group",
  "booleanOperation": -1,
  "clippingMaskMode": 0,
  "do_objectID": "809A8D3D-EEBE-470A-8BA9-3A13DECE047F",
  "exportOptions": {
    "_class": "exportOptions",
    "exportFormats": [
    ],
    "includedLayerIds": [
    ],
    "layerOptions": 0,
    "shouldTrim": false
  },
  "frame": {
    "_class": "rect",
    "constrainProportions": true,
    "do_objectID": "E21876A3-E1FD-4025-B317-6F1935A18303",
    "height": 100,
    "width": 939,
    "x": -23,
    "y": 136
  },
  "groupLayout": {
    "_class": "MSImmutableFreeformGroupLayout",
    "do_objectID": "15595444-2EAC-435B-AFF1-6C084593FDB9"
  },
  "hasClickThrough": false,
  "hasClippingMask": false,
  "isFixedToViewport": false,
  "isFlippedHorizontal": false,
  "isFlippedVertical": false,
  "isLocked": false,
  "isVisible": true,
  "layerListExpandedType": 0,
  "layers": [
    {
      "class": "rectangle",
      "id": "86983693-D5CA-4FCC-AB04-9DD53F10CBE4"
    },
    {
      "class": "bitmap",
      "id": "AC14535C-623B-4F28-8FA2-9DF271E29360"
    }
  ],
  "name": "Olbico-clientlogos",
  "nameIsFixed": false,
  "resizingConstraint": 63,
  "resizingType": 0,
  "rotation": 0,
  "shouldBreakMaskChain": false,
  "style": {
    "_class": "style",
    "do_objectID": "7A14F409-712B-4576-9FC7-82F3BDCA74F8",
    "endMarkerType": 0,
    "miterLimit": 10,
    "startMarkerType": 0,
    "windingRule": 1
  }
}