{
  "_class": "symbolInstance",
  "booleanOperation": -1,
  "clippingMaskMode": 0,
  "do_objectID": "D5BE86AB-A862-47B4-AD6D-11B72E2DF653",
  "exportOptions": {
    "_class": "exportOptions",
    "exportFormats": [
    ],
    "includedLayerIds": [
    ],
    "layerOptions": 0,
    "shouldTrim": false
  },
  "frame": {
    "_class": "rect",
    "constrainProportions": true,
    "do_objectID": "5608F1DA-2B2C-4226-992E-67F3CAA6A448",
    "height": 155.9251559251559,
    "width": 375,
    "x": 0,
    "y": 119.0000000000001
  },
  "hasClippingMask": false,
  "horizontalSpacing": 0,
  "isFixedToViewport": false,
  "isFlippedHorizontal": false,
  "isFlippedVertical": false,
  "isLocked": false,
  "isVisible": true,
  "layerListExpandedType": 0,
  "name": "Illustration/demo-cta",
  "nameIsFixed": false,
  "overrideValues": [
  ],
  "resizingConstraint": 63,
  "resizingType": 0,
  "rotation": 0,
  "scale": 1,
  "shouldBreakMaskChain": false,
  "style": {
    "_class": "style",
    "contextSettings": {
      "_class": "graphicsContextSettings",
      "blendMode": 0,
      "do_objectID": "E68F44F5-99FE-46FF-B9E9-4206E3B7B432",
      "opacity": 0.33
    },
    "do_objectID": "573DD7EC-8A1D-4CC6-A705-899ADADDD719",
    "endMarkerType": 0,
    "miterLimit": 10,
    "startMarkerType": 0,
    "windingRule": 1
  },
  "symbolID": "FBFDCFEA-91C4-4080-BFEB-E7DA7D90E7B5",
  "verticalSpacing": 0
}